octoprint_grbl_plugin/__init__.py
octoprint_grbl_plugin/plugin.py
octoprint_grbl_plugin-1.0.2.dist-info/METADATA
octoprint_grbl_plugin-1.0.2.dist-info/RECORD
octoprint_grbl_plugin-1.0.2.dist-info/WHEEL
octoprint_grbl_plugin-1.0.2.dist-info/entry_points.txt
octoprint_grbl_plugin-1.0.2.dist-info/top_level.txt
