Metadata-Version: 2.1
Name: octoprint-grbl-plugin
Version: 1.0.2
Summary: Support GRBL type CNC & Laser machines
Home-page: https://github.com/mic159/octoprint-grbl-plugin
Author: mic159
Author-email: mic159@gmail.com
License: MIT
Keywords: octoprint,grbl,gcode,cnc,laser
Platform: UNKNOWN
